gallifrey/__init__.py
gallifrey/data.py
gallifrey/gpconfig.py
gallifrey/inference/__init__.py
gallifrey/inference/hmc.py
gallifrey/inference/parameter_rejuvenation.py
gallifrey/inference/rejuvenation.py
gallifrey/inference/smc.py
gallifrey/inference/state.py
gallifrey/inference/transforms.py
gallifrey/kernels/__init__.py
gallifrey/kernels/atoms.py
gallifrey/kernels/library.py
gallifrey/kernels/prior.py
gallifrey/kernels/tree.py
gallifrey/model.py
gallifrey/moves/__init__.py
gallifrey/moves/acceptance_probability.py
gallifrey/moves/detach_attach.py
gallifrey/moves/noise_proposal.py
gallifrey/moves/particle_move.py
gallifrey/moves/subtree_replace.py
gallifrey/parameter.py
gallifrey/particles.py
gallifrey/schedule.py
gallifrey/utils/__init__.py
gallifrey/utils/probability_calculations.py
gallifrey/utils/tree_helper.py
gallifrey/utils/typing.py
gallifrey-0.1.1.dist-info/LICENSE
gallifrey-0.1.1.dist-info/METADATA
gallifrey-0.1.1.dist-info/WHEEL
gallifrey-0.1.1.dist-info/RECORD
