Metadata-Version: 2.3
Name: gallifrey
Version: 0.1.1
Summary: A JAX-based gaussian process structure learning package for time series modelling.
License: Apache 2.0
Author: Chris Boettner
Author-email: boettnec@gmail.com
Requires-Python: >=3.10
Classifier: License :: Other/Proprietary License
Classifier: Programming Language :: Python :: 3
Classifier: Programming Language :: Python :: 3.10
Classifier: Programming Language :: Python :: 3.11
Classifier: Programming Language :: Python :: 3.12
Classifier: Programming Language :: Python :: 3.13
Requires-Dist: beartype (>=0.19.0,<0.20.0)
Requires-Dist: blackjax (>=1.2.5,<2.0.0)
Requires-Dist: equinox (>=0.11.11,<0.12.0)
Requires-Dist: flax (>=0.10.3,<0.11.0)
Requires-Dist: jax (>=0.5.0,<0.6.0)
Requires-Dist: tensorflow-probability (>=0.25.0,<0.26.0)
